LICENSE
MANIFEST.in
README.md
pyproject.toml
setup.py
skillit/__init__.py
skillit/py.typed
skillit/requirements-dev.txt
skillit/requirements.txt
skillit.egg-info/PKG-INFO
skillit.egg-info/SOURCES.txt
skillit.egg-info/dependency_links.txt
skillit.egg-info/requires.txt
skillit.egg-info/top_level.txt
skillit/play/__init__.py
skillit/play/player.py
skillit/recipes/__init__.py
skillit/recipes/camera.py
skillit/recipes/maps.py
skillit/recipes/move_joint_a_little.py
skillit/recipes/setup_zeroing.py
skillit/record/__init__.py
skillit/record/recorder.py
skillit/tools/__init__.py
skillit/tools/resample.py
skillit/tools/skills.py
tests/test_dummy.py