Metadata-Version: 2.2
Name: skillit
Version: 0.2.0
Summary: A package that lets you chef up new skills for KOS-compatible robots
Home-page: https://github.com/kscalelabs/skillit
Author: Wesley Maa
Requires-Python: >=3.11
License-File: LICENSE
Requires-Dist: pykos
Provides-Extra: dev
Requires-Dist: black>=24.1.1; extra == "dev"
Requires-Dist: isort>=5.13.2; extra == "dev"
Requires-Dist: ruff>=0.2.1; extra == "dev"
Requires-Dist: matplotlib; extra == "dev"
Requires-Dist: numpy; extra == "dev"
Dynamic: author
Dynamic: description
Dynamic: description-content-type
Dynamic: home-page
Dynamic: provides-extra
Dynamic: requires-dist
Dynamic: requires-python
Dynamic: summary
